lastmile_auto_eval/__init__.py
lastmile_auto_eval/api.py
lastmile_auto_eval/__generated__/common_pb2.py
lastmile_auto_eval/__generated__/common_pb2.pyi
lastmile_auto_eval/__generated__/common_pb2_grpc.py
lastmile_auto_eval/__generated__/eval_api_pb2.py
lastmile_auto_eval/__generated__/eval_api_pb2.pyi
lastmile_auto_eval/__generated__/eval_api_pb2_grpc.py
lastmile_auto_eval/__generated__/evaluation_job_pb2.py
lastmile_auto_eval/__generated__/evaluation_job_pb2.pyi
lastmile_auto_eval/__generated__/evaluation_job_pb2_grpc.py
lastmile_auto_eval/__generated__/status_pb2.py
lastmile_auto_eval/__generated__/status_pb2.pyi
lastmile_auto_eval/__generated__/status_pb2_grpc.py
lastmile_auto_eval/utils/__init__.py
lastmile_auto_eval/utils/constants.py
lastmile_auto_eval/utils/helpers.py
lastmile_auto_eval/utils/type_defs.py
lastmile_auto_eval-0.0.10.dist-info/METADATA
lastmile_auto_eval-0.0.10.dist-info/WHEEL
lastmile_auto_eval-0.0.10.dist-info/top_level.txt
lastmile_auto_eval-0.0.10.dist-info/RECORD
