Metadata-Version: 2.1
Name: lastmile_auto_eval
Version: 0.0.10
Summary: An API for using metric models (either provided by default or fine-tuned yourself) to evaluate LLMs.
Author: LastMile AI
Classifier: Intended Audience :: Developers
Classifier: Programming Language :: Python :: 3
Requires-Python: >=3.10
Requires-Dist: python-dotenv
Requires-Dist: pandas>=2.1.2
Requires-Dist: grpcio
Requires-Dist: grpcio-tools
